{"data":"{\n  \"status\": \"success\",\n  \"map\": {\n    \"__content__\": {\n      \"totalNumberOfResults\": 1,\n      \"vouchers\": [\n        {\n          \"code\": \"FSPRO00000007\",\n\"voucherCode\":\"FSPRO00000007001\",\n          \"value\": \"7\",\n          \"name\": \"voucherName7\",\n          \"voucherType\": \"oldMachineVoucher\",\n          \"status\": \"PUBLISHED\",\n          \"scopes\": [\n            {\n              \"isWholeCountry\": false,\n              \"channelName\": \"B2C\",\n              \"provinceNames\": null,\n              \"cityNames\": [\n                \"南京\"\n              ],\n              \"pointOfServices\": null\n            }\n          ],\n          \"totalVouchers\": \"100\"\n        },\n                {\n          \"code\": \"FSPRO00000008\",\n\"voucherCode\":\"FSPRO00000008001\",\n          \"value\": \"8\",\n          \"name\": \"voucherName8\",\n          \"voucherType\": \"packageVoucher\",\n          \"status\": \"UNPUBLISHED\",\n          \"scopes\": [\n            {\n              \"isWholeCountry\": true,\n              \"channelName\": \"B2C\",\n              \"provinceNames\": null,\n              \"cityNames\": [\n                \"南京\"\n              ],\n              \"pointOfServices\": null\n            }\n          ],\n          \"totalVouchers\": \"99\"\n        },\n                {\n          \"code\": \"FSPRO00000009\",\n\"voucherCode\":\"FSPRO00000009001\",\n          \"value\": \"9\",\n          \"name\": \"voucherName9\",\n          \"voucherType\": \"prestoredVoucher\",\n          \"status\": \"PUBLISHED\",\n          \"scopes\": [\n            {\n              \"isWholeCountry\": false,\n              \"channelName\": \"B2C\",\n              \"provinceNames\": null,\n              \"cityNames\": [\n                \"南京\"\n              ],\n              \"pointOfServices\": [\"玄武门\"]\n            }\n          ],\n          \"totalVouchers\": \"98\"\n        },\n                {\n          \"code\": \"FSPRO00000010\",\n\"voucherCode\":\"FSPRO00000010001\",\n          \"value\": \"10\",\n          \"name\": \"voucherName10\",\n          \"voucherType\": \"smallCashVoucher\",\n          \"status\": \"UNPUBLISHED\",\n          \"scopes\": [\n            {\n              \"isWholeCountry\": false,\n              \"channelName\": \"B2C\",\n              \"provinceNames\": [\"江苏\"],\n              \"cityNames\": [],\n              \"pointOfServices\": null\n            }\n          ],\n          \"totalVouchers\": \"97\"\n        }\n      ]\n    }\n  }\n}"}